kernel_quantile_regression/__init__.py
kernel_quantile_regression/kqr.py
kernel_quantile_regression-0.0.15.dist-info/METADATA
kernel_quantile_regression-0.0.15.dist-info/WHEEL
kernel_quantile_regression-0.0.15.dist-info/licenses/LICENSE
kernel_quantile_regression-0.0.15.dist-info/RECORD
