Metadata-Version: 2.3
Name: kernel_quantile_regression
Version: 0.0.15
Summary: Kernel quantile regression
Project-URL: Homepage, https://github.com/luca-pernigo/kernel_quantile_regression
Author-email: Luca Pernigo <luca.pernigo@usi.ch>
License-File: LICENSE
Classifier: License :: OSI Approved :: MIT License
Classifier: Operating System :: OS Independent
Classifier: Programming Language :: Python :: 3
Requires-Python: >=3.10
